mlflow_export_import/__init__.py
mlflow_export_import/bulk/__init__.py
mlflow_export_import/bulk/bulk_utils.py
mlflow_export_import/bulk/export_all.py
mlflow_export_import/bulk/export_experiments.py
mlflow_export_import/bulk/export_models.py
mlflow_export_import/bulk/import_experiments.py
mlflow_export_import/bulk/import_models.py
mlflow_export_import/bulk/model_utils.py
mlflow_export_import/common/__init__.py
mlflow_export_import/common/click_options.py
mlflow_export_import/common/databricks_cli_utils.py
mlflow_export_import/common/dump_run.py
mlflow_export_import/common/filesystem.py
mlflow_export_import/common/find_artifacts.py
mlflow_export_import/common/http_client.py
mlflow_export_import/common/io_utils.py
mlflow_export_import/common/iterators.py
mlflow_export_import/common/mlflow_utils.py
mlflow_export_import/common/model_utils.py
mlflow_export_import/common/pkg_version.py
mlflow_export_import/common/source_tags.py
mlflow_export_import/common/timestamp_utils.py
mlflow_export_import/common/user_agent_header.py
mlflow_export_import/common/utils.py
mlflow_export_import/experiment/__init__.py
mlflow_export_import/experiment/export_experiment.py
mlflow_export_import/experiment/import_experiment.py
mlflow_export_import/model/__init__.py
mlflow_export_import/model/export_model.py
mlflow_export_import/model/import_model.py
mlflow_export_import/model/list_registered_models.py
mlflow_export_import/notebook/__init__.py
mlflow_export_import/notebook/download_notebook.py
mlflow_export_import/run/__init__.py
mlflow_export_import/run/export_run.py
mlflow_export_import/run/import_run.py
mlflow_export_import/run/run_data_importer.py
mlflow_export_import/workflow_api/__init__.py
mlflow_export_import/workflow_api/cred_utils.py
mlflow_export_import/workflow_api/log_utils.py
mlflow_export_import/workflow_api/run_submit.py
mlflow_export_import/workflow_api/utils.py
mlflow_export_import/workflow_api/workflow_api_client.py
mlflow_export_import-1.2.0.dist-info/LICENSE.txt
mlflow_export_import-1.2.0.dist-info/METADATA
mlflow_export_import-1.2.0.dist-info/WHEEL
mlflow_export_import-1.2.0.dist-info/entry_points.txt
mlflow_export_import-1.2.0.dist-info/top_level.txt
mlflow_export_import-1.2.0.dist-info/RECORD
