Metadata-Version: 2.1
Name: mlflow-export-import
Version: 1.2.0
Summary: Copy MLflow objects (experiments, runs or registered models) to another tracking server
Home-page: https://github.com/mlflow/mlflow-export-import
Author: Andre Mesarovic
License: Apache License 2.0
Project-URL: Bug Tracker, https://github.com/mlflow/mlflow-export-import/issues
Project-URL: Documentation, https://github.com/mlflow/mlflow-export-import/blob/master/README.md
Project-URL: Source Code, https://github.com/mlflow/mlflow-export-import/
Keywords: mlflow ml ai
Platform: UNKNOWN
Classifier: Intended Audience :: Developers
Classifier: Programming Language :: Python :: 3.8
Classifier: Operating System :: OS Independent
Requires-Python: >=3.8
Requires-Dist: mlflow (>=1.28.0)
Requires-Dist: wheel
Requires-Dist: pytest (>=7.2.0)
Requires-Dist: pytest-html
Requires-Dist: shortuuid
